README.txt
setup.py
pyILT.egg-info/PKG-INFO
pyILT.egg-info/SOURCES.txt
pyILT.egg-info/dependency_links.txt
pyILT.egg-info/top_level.txt
pythermo/__init__.py
pythermo/proplist.py
pythermo/report.py
pythermo/version.py