Metadata-Version: 1.1
Name: pyILT
Version: 0.1.2
Summary: Extraction of data from ILThermo
Home-page: UNKNOWN
Author: Joao Ines - FCT-UNL
Author-email: j.ines@fct.unl.pt
License: MIT
Keywords: ILThermo_DB
Platform: UNKNOWN
Classifier: Development Status :: 5 - Production/Stable
Classifier: Intended Audience :: Education
Classifier: Operating System :: POSIX :: Linux
Classifier: License :: OSI Approved :: MIT License
Classifier: Programming Language :: Python :: 3
